pytest_bonsai/__init__.py
pytest_bonsai/conftest.py
pytest_bonsai/parametrize.py
pytest_bonsai-0.0.2.dist-info/licenses/LICENSE
pytest_bonsai-0.0.2.dist-info/METADATA
pytest_bonsai-0.0.2.dist-info/WHEEL
pytest_bonsai-0.0.2.dist-info/entry_points.txt
pytest_bonsai-0.0.2.dist-info/top_level.txt
pytest_bonsai-0.0.2.dist-info/RECORD
