Metadata-Version: 2.4
Name: pytest-bonsai
Version: 0.0.2
Author-email: Michał 'Khorne' Lowas-Rzechonek <michal@rzechonek.net>
License-File: LICENSE
Requires-Dist: pytest>=6
Provides-Extra: dev
Requires-Dist: black; extra == "dev"
Requires-Dist: mkdocs; extra == "dev"
Requires-Dist: mkdocstrings[python]; extra == "dev"
Dynamic: license-file
